setup.py
dynadotpy/__init__.py
dynadotpy/client.py
dynadotpy.egg-info/PKG-INFO
dynadotpy.egg-info/SOURCES.txt
dynadotpy.egg-info/dependency_links.txt
dynadotpy.egg-info/not-zip-safe
dynadotpy.egg-info/requires.txt
dynadotpy.egg-info/top_level.txt