Metadata-Version: 1.1
Name: dynadotpy
Version: 0.1.0
Summary: Simple Python wrapper for dynadot.com v2 API.
Home-page: https://github.com/brack3t/dynadotpy
Author: Chris Jones <chris@brack3t.com>
Author-email: chris@brack3t.com
License: BSD
Keywords: python,dynadot
Platform: UNKNOWN
Classifier: Programming Language :: Python :: 2 :: Only
Classifier: License :: OSI Approved :: BSD License
Classifier: Topic :: Software Development :: Libraries :: Python Modules
Classifier: Environment :: Web Environment
Classifier: Natural Language :: English
Classifier: Operating System :: OS Independent
Classifier: Topic :: Internet
Classifier: Intended Audience :: Information Technology
